copernicus_marine_client/__init__.py
copernicus_marine_client/catalogue_parser/__init__.py
copernicus_marine_client/catalogue_parser/catalogue_parser.py
copernicus_marine_client/catalogue_parser/request_structure.py
copernicus_marine_client/command_line_interface/__init__.py
copernicus_marine_client/command_line_interface/copernicus_marine.py
copernicus_marine_client/command_line_interface/exception_handler.py
copernicus_marine_client/command_line_interface/group_describe.py
copernicus_marine_client/command_line_interface/group_get.py
copernicus_marine_client/command_line_interface/group_login.py
copernicus_marine_client/command_line_interface/group_subset.py
copernicus_marine_client/command_line_interface/utils.py
copernicus_marine_client/core_functions/credentials_utils.py
copernicus_marine_client/core_functions/deprecated.py
copernicus_marine_client/core_functions/deprecated_options.py
copernicus_marine_client/core_functions/describe.py
copernicus_marine_client/core_functions/exceptions.py
copernicus_marine_client/core_functions/get.py
copernicus_marine_client/core_functions/login.py
copernicus_marine_client/core_functions/models.py
copernicus_marine_client/core_functions/services_utils.py
copernicus_marine_client/core_functions/sessions.py
copernicus_marine_client/core_functions/subset.py
copernicus_marine_client/core_functions/utils.py
copernicus_marine_client/core_functions/versions_verifier.py
copernicus_marine_client/download_functions/common_download.py
copernicus_marine_client/download_functions/download_arco_series.py
copernicus_marine_client/download_functions/download_ftp.py
copernicus_marine_client/download_functions/download_get.py
copernicus_marine_client/download_functions/download_motu.py
copernicus_marine_client/download_functions/download_opendap.py
copernicus_marine_client/download_functions/download_original_files.py
copernicus_marine_client/download_functions/subset_parameters.py
copernicus_marine_client/download_functions/subset_xarray.py
copernicus_marine_client-0.10.7.dist-info/WHEEL
copernicus_marine_client-0.10.7.dist-info/entry_points.txt
copernicus_marine_client-0.10.7.dist-info/METADATA
copernicus_marine_client-0.10.7.dist-info/RECORD
