Metadata-Version: 2.1
Name: copernicus-marine-client
Version: 0.10.7
Summary: 
Author: Copernicus Marine User Support
Author-email: servicedesk.cmems@mercator-ocean.eu
Requires-Python: >=3.9,<3.12
Classifier: Programming Language :: Python :: 3
Classifier: Programming Language :: Python :: 3.9
Classifier: Programming Language :: Python :: 3.10
Classifier: Programming Language :: Python :: 3.11
Requires-Dist: aiohttp (>=3.8.5,<4.0.0)
Requires-Dist: boto3 (>=1.25,<1.34)
Requires-Dist: cachier (>=2.2.1,<3.0.0)
Requires-Dist: click (>=8.0.4,<9.0.0)
Requires-Dist: dask (>=2022,<2024)
Requires-Dist: lxml (>=4.9.0,<5.0.0)
Requires-Dist: motuclient (>=1.8.4,<2.0.0)
Requires-Dist: nest-asyncio (>=1.5.8,<2.0.0)
Requires-Dist: netCDF4 (>=1.6.3,<2.0.0)
Requires-Dist: pydap (>=3.2.2,<4.0.0)
Requires-Dist: pystac (>=1.8.3,<2.0.0)
Requires-Dist: requests (>=2.27.1,<3.0.0)
Requires-Dist: semver (>=3.0.2,<4.0.0)
Requires-Dist: setuptools (>=68.2.2,<69.0.0)
Requires-Dist: tqdm (>=4.65.0,<5.0.0)
Requires-Dist: xarray (>=2023.9,<2023.12)
Requires-Dist: zarr (>=2.13.3,<3.0.0)
